labware_domain_models/__init__.py
labware_domain_models/barcoded_sbs_labware.py
labware_domain_models/exceptions.py
labware_domain_models/labware_definitions.py
labware_domain_models-0.3.2.dist-info/LICENSE
labware_domain_models-0.3.2.dist-info/METADATA
labware_domain_models-0.3.2.dist-info/WHEEL
labware_domain_models-0.3.2.dist-info/top_level.txt
labware_domain_models-0.3.2.dist-info/RECORD
